[
    {
        "Job Title": "Devops Engineer",
        "Company": "Birlasoft Limited",
        "Experience": "4 - 6 Years",
        "Location": "Gurgaon / Gurugram",
        "Posted": "6 days ago"
    },
    {
        "Job Title": "Devops Engineer",
        "Company": "Kyndryl",
        "Experience": "5 - 7 Years",
        "Location": "Noida, India",
        "Posted": "4 days ago"
    },
    {
        "Job Title": "Devops Engineer",
        "Company": "Kyndryl",
        "Experience": "5 - 7 Years",
        "Location": "Bengaluru / Bangalore, India",
        "Posted": "5 days ago"
    },
    {
        "Job Title": "Devops Engineer",
        "Company": "Domnic Lewis International",
        "Experience": "5 - 12 Years",
        "Location": "Bengaluru / Bangalore, India",
        "Posted": "2 days ago"
    },
    {
        "Job Title": "Devops engineer",
        "Company": "VIBRANT STAFFING SOLUTIONS PVT LTD",
        "Experience": "Fresher",
        "Location": "India, Nashik",
        "Posted": "3 days ago"
    },
    {
        "Job Title": "Devops Engineer",
        "Company": "People Prime Worldwide Private Limited",
        "Experience": "6 - 8 Years",
        "Location": "Pune",
        "Posted": "3 days ago"
    },
    {
        "Job Title": "Devops Engineer",
        "Company": "Whitefield Careers",
        "Experience": "5 - 7 Years",
        "Location": "Bengaluru / Bangalore, India",
        "Posted": "3 days ago"
    },
    {
        "Job Title": "DevOps Engineer",
        "Company": "MicroGenesis TechSoft",
        "Experience": "5 - 7 Years",
        "Location": "Bengaluru / Bangalore, India",
        "Posted": "4 days ago"
    },
    {
        "Job Title": "Devops Engineer",
        "Company": "Kapstag Workforce Solutions Private Limited",
        "Experience": "4 - 9 Years",
        "Location": "Pune",
        "Posted": "1 days ago"
    },
    {
        "Job Title": "Devops Engineer",
        "Company": "Kyndryl",
        "Experience": "5 - 7 Years",
        "Location": "Bengaluru / Bangalore, India",
        "Posted": "4 days ago"
    },
    {
        "Job Title": "Devops Engineer",
        "Company": "Strongwill india pvt ltd",
        "Experience": "5 - 7 Years",
        "Location": "Bengaluru / Bangalore, India",
        "Posted": "4 days ago"
    },
    {
        "Job Title": "DevOps Engineer",
        "Company": "Capermint Technologies",
        "Experience": "3 - 5 Years",
        "Location": "Ahmedabad, India",
        "Posted": "2 days ago"
    }
]